{"key": "D", "note1": {"note": "A5", "rhythm": 0.25, "haspot": false, "gongchi": "五", "word": "套"}, "note2": {"note": "G4", "rhythm": 0.25, "haspot": false, "gongchi": "六", "word": "寫"}, "note3": {"note": "E4", "rhythm": 0.25, "haspot": false, "gongchi": "工", "word": ""}, "note4": {"note": "E4", "rhythm": 0.125, "haspot": false, "gongchi": "工", "word": "皇"}, "note5": {"note": "G4", "rhythm": 0.125, "haspot": false, "gongchi": "六", "word": ""}, "note6": {"note": "A5", "rhythm": 1.0, "haspot": false, "gongchi": "五(━)", "word": "宣"}, "juhao1": {"word": "。"}, "note7": {"note": "D5", "rhythm": 0.25, "haspot": false, "gongchi": "伬(□)", "word": "倩"}, "note8": {"note": "C5", "rhythm": 0.25, "haspot": false, "gongchi": "仩", "word": ""}, "note9": {"note": "A5", "rhythm": 0.25, "haspot": false, "gongchi": "五(丶)", "word": "嬌"}, "note10": {"note": "G4", "rhythm": 0.25, "haspot": false, "gongchi": "六", "word": "娘"}, "note11": {"note": "A5", "rhythm": 0.25, "haspot": true, "gongchi": "五(□)", "word": ""}, "note12": {"note": "G4", "rhythm": 0.125, "haspot": false, "gongchi": "六", "word": ""}, "note13": {"note": "E4", "rhythm": 0.25, "haspot": false, "gongchi": "工(丶)", "word": "假"}, "note14": {"note": "G4", "rhythm": 0.125, "haspot": false, "gongchi": "六", "word": ""}, "note15": {"note": "A5", "rhythm": 0.125, "haspot": false, "gongchi": "", "word": ""}, "note16": {"note": "D5", "rhythm": 0.25, "haspot": false, "gongchi": "伬(□)", "word": "做"}, "note17": {"note": "C5", "rhythm": 0.25, "haspot": false, "gongchi": "仩", "word": ""}, "note18": {"note": "A5", "rhythm": 0.25, "haspot": true, "gongchi": "五(丶)", "word": ""}, "note19": {"note": "C5", "rhythm": 0.125, "haspot": false, "gongchi": "仩", "word": ""}, "note20": {"note": "A5", "rhythm": 0.25, "haspot": false, "gongchi": "五(□)", "word": ""}, "note21": {"note": "G4", "rhythm": 0.25, "haspot": false, "gongchi": "六", "word": ""}, "juhao2": {"word": "。"}, "note22": {"note": "E4", "rhythm": 0.25, "haspot": true, "gongchi": "工(丶)", "word": "中"}, "note23": {"note": "G4", "rhythm": 0.125, "haspot": false, "gongchi": "六", "word": ""}, "note24": {"note": "E4", "rhythm": 0.5, "haspot": false, "gongchi": "工(□)", "word": ""}, "note25": {"note": "", "rhythm": "", "haspot": false, "gongchi": "尺", "word": ""}, "note26": {"note": "D4", "rhythm": 0.25, "haspot": true, "gongchi": "尺(丶)", "word": "官"}, "note27": {"note": "E4", "rhythm": 0.125, "haspot": false, "gongchi": "工", "word": ""}, "note28": {"note": "D4", "rhythm": 1.0, "haspot": false, "gongchi": "尺(□━)", "word": ""}, "note29": {"note": "E4", "rhythm": 0.5, "haspot": true, "gongchi": "工(□)", "word": "裝"}, "note30": {"note": "G4", "rhythm": 0.25, "haspot": false, "gongchi": "六", "word": ""}, "note31": {"note": "E4", "rhythm": 0.125, "haspot": true, "gongchi": "工(□)", "word": ""}, "note32": {"note": "E4", "rhythm": 0.0625, "haspot": false, "gongchi": "尺", "word": ""}, "note33": {"note": "D4", "rhythm": 0.25, "haspot": false, "gongchi": "", "word": ""}, "note34": {"note": "E4", "rhythm": 0.25, "haspot": false, "gongchi": "工(丶)", "word": "扮"}, "note35": {"note": "D4", "rhythm": 0.25, "haspot": false, "gongchi": "尺", "word": ""}, "note36": {"note": "C4", "rhythm": 0.5, "haspot": false, "gongchi": "上(□)", "word": ""}, "juhao3": {"word": "。"}, "note37": {"note": "G4", "rhythm": 0.25, "haspot": false, "gongchi": "六(丶)", "word": "賣"}, "note38": {"note": "A5", "rhythm": 0.25, "haspot": false, "gongchi": "五", "word": ""}, "note39": {"note": "G4", "rhythm": 0.25, "haspot": true, "gongchi": "六(□)", "word": ""}, "note40": {"note": "E4", "rhythm": 0.125, "haspot": false, "gongchi": "工", "word": ""}, "note41": {"note": "D4", "rhythm": 0.25, "haspot": false, "gongchi": "尺(丶)", "word": "藥"}, "note42": {"note": "E4", "rhythm": 0.125, "haspot": false, "gongchi": "工", "word": ""}, "note43": {"note": "G4", "rhythm": 0.125, "haspot": false, "gongchi": "六", "word": ""}, "note44": {"note": "E4", "rhythm": 0.25, "haspot": true, "gongchi": "工(□)", "word": ""}, "note45": {"note": "D4", "rhythm": 0.125, "haspot": false, "gongchi": "尺", "word": ""}, "note46": {"note": "C4", "rhythm": 0.25, "haspot": false, "gongchi": "上(丶)", "word": "酒"}, "note47": {"note": "D4", "rhythm": 0.25, "haspot": false, "gongchi": "尺", "word": ""}, "juhao4": {"word": "。"}, "note48": {"note": "G3", "rhythm": 0.25, "haspot": false, "gongchi": "合(□)", "word": "藥"}, "note49": {"note": "A4", "rhythm": 0.125, "haspot": false, "gongchi": "四", "word": "取"}, "note50": {"note": "C4", "rhythm": 0.125, "haspot": false, "gongchi": "上", "word": ""}, "note51": {"note": "D4", "rhythm": 0.5, "haspot": true, "gongchi": "尺", "word": "佳"}, "note52": {"note": "E4", "rhythm": 0.125, "haspot": true, "gongchi": "工", "word": ""}, "note53": {"note": "D4", "rhythm": 0.0625, "haspot": false, "gongchi": "尺", "word": ""}, "note54": {"note": "C4", "rhythm": 0.5, "haspot": false, "gongchi": "上(丶)", "word": "人"}, "note55": {"note": "D4", "rhythm": 1.0, "haspot": false, "gongchi": "尺(□━)", "word": ""}, "note56": {"note": "A5", "rhythm": 1.0, "haspot": false, "gongchi": "五(□)", "word": "氣"}, "note57": {"note": "G4", "rhythm": 0.25, "haspot": true, "gongchi": "六", "word": ""}, "note58": {"note": "A5", "rhythm": 0.125, "haspot": false, "gongchi": "五", "word": ""}, "note59": {"note": "E4", "rhythm": 0.25, "haspot": false, "gongchi": "工(丶)", "word": "斷"}, "note60": {"note": "D4", "rhythm": 0.25, "haspot": false, "gongchi": "尺", "word": ""}, "note61": {"note": "C4", "rhythm": 0.5, "haspot": false, "gongchi": "上(□)", "word": ""}, "juhao5": {"word": "。"}, "note62": {"note": "E4", "rhythm": 0.25, "haspot": false, "gongchi": "工(丶)", "word": "何"}, "note63": {"note": "G4", "rhythm": 0.5, "haspot": false, "gongchi": "六(丶)", "word": ""}, "note64": {"note": "A5", "rhythm": 0.125, "haspot": true, "gongchi": "五", "word": ""}, "note65": {"note": "G4", "rhythm": 0.0625, "haspot": false, "gongchi": "", "word": ""}, "note66": {"note": "E4", "rhythm": 0.25, "haspot": false, "gongchi": "工(丶)", "word": "難"}, "note67": {"note": "G4", "rhythm": 0.5, "haspot": true, "gongchi": "六", "word": ""}, "note68": {"note": "A5", "rhythm": 0.125, "haspot": false, "gongchi": "五", "word": ""}, "note69": {"note": "#", "rhythm": 0.0625, "haspot": false, "gongchi": "", "word": ""}, "note70": {"note": "B5", "rhythm": 0.0625, "haspot": false, "gongchi": "六", "word": ""}, "note71": {"note": "A5", "rhythm": 0.25, "haspot": false, "gongchi": "六(□)", "word": ""}, "note72": {"note": "G4", "rhythm": 0.5, "haspot": false, "gongchi": "", "word": ""}, "juhao6": {"word": "。"}, "note73": {"note": "A5", "rhythm": 0.5, "haspot": false, "gongchi": "五(丶)", "word": "自"}, "note74": {"note": "G4", "rhythm": 0.125, "haspot": false, "gongchi": "六(□)", "word": "有"}, "note75": {"note": "#", "rhythm": 0.0625, "haspot": false, "gongchi": "", "word": ""}, "note76": {"note": "G4", "rhythm": 0.0625, "haspot": false, "gongchi": "工", "word": ""}, "note77": {"note": "E4", "rhythm": 0.125, "haspot": false, "gongchi": "六", "word": ""}, "note78": {"note": "G4", "rhythm": 0.125, "haspot": false, "gongchi": "五(丶)", "word": ""}, "note79": {"note": "A5", "rhythm": 0.25, "haspot": true, "gongchi": "仩", "word": ""}, "note80": {"note": "C5", "rhythm": 0.125, "haspot": false, "gongchi": "五(□)", "word": ""}, "note81": {"note": "A5", "rhythm": 0.125, "haspot": true, "gongchi": "六", "word": ""}, "note82": {"note": "C5", "rhythm": 0.0625, "haspot": false, "gongchi": "工", "word": ""}, "note83": {"note": "A5", "rhythm": 0.0625, "haspot": false, "gongchi": "", "word": ""}, "note84": {"note": "G4", "rhythm": 0.0625, "haspot": false, "gongchi": "", "word": ""}, "note85": {"note": "E4", "rhythm": 0.125, "haspot": false, "gongchi": "", "word": ""}, "note86": {"note": "D4", "rhythm": 0.25, "haspot": false, "gongchi": "尺(丶)", "word": "靈"}, "note87": {"note": "E4", "rhythm": 0.125, "haspot": false, "gongchi": "工", "word": ""}, "note88": {"note": "G4", "rhythm": 0.125, "haspot": false, "gongchi": "六", "word": ""}, "note89": {"note": "E4", "rhythm": 0.5, "haspot": false, "gongchi": "工(□)", "word": ""}, "note90": {"note": "", "rhythm": "", "haspot": false, "gongchi": "尺", "word": ""}, "note91": {"note": "D4", "rhythm": 0.5, "haspot": false, "gongchi": "尺(丶)", "word": "丹"}, "juhao7": {"word": "。"}, "note92": {"note": "C5", "rhythm": 0.125, "haspot": false, "gongchi": "仩(□)", "word": "死"}, "note93": {"note": "A5", "rhythm": 0.125, "haspot": false, "gongchi": "五", "word": ""}, "note94": {"note": "D5", "rhythm": 0.125, "haspot": false, "gongchi": "伬", "word": "後"}, "note95": {"note": "C5", "rhythm": 0.125, "haspot": false, "gongchi": "仩", "word": ""}, "note96": {"note": "A5", "rhythm": 0.25, "haspot": false, "gongchi": "五(丶)", "word": "重"}, "note97": {"note": "C5", "rhythm": 0.125, "haspot": false, "gongchi": "仩", "word": ""}, "note98": {"note": "D5", "rhythm": 0.125, "haspot": false, "gongchi": "伬", "word": ""}, "note99": {"note": "C5", "rhythm": 0.5, "haspot": false, "gongchi": "仩(□)", "word": ""}, "note100": {"note": "", "rhythm": "", "haspot": false, "gongchi": "五", "word": ""}, "note101": {"note": "A5", "rhythm": 0.25, "haspot": true, "gongchi": "五(丶)", "word": "生"}, "note102": {"note": "C5", "rhythm": 0.125, "haspot": false, "gongchi": "仩", "word": ""}, "note103": {"note": "A5", "rhythm": 0.5, "haspot": false, "gongchi": "五(□)", "word": ""}, "juhao8": {"word": "。"}, "note104": {"note": "G4", "rhythm": 0.25, "haspot": false, "gongchi": "六(丶)", "word": "不"}, "note105": {"note": "A5", "rhythm": 0.25, "haspot": false, "gongchi": "五", "word": ""}, "note106": {"note": "G4", "rhythm": 0.5, "haspot": false, "gongchi": "六(□)", "word": "須"}, "note107": {"note": "A5", "rhythm": 0.25, "haspot": true, "gongchi": "五(丶)", "word": ""}, "note108": {"note": "G4", "rhythm": 0.125, "haspot": false, "gongchi": "六", "word": ""}, "note109": {"note": "E4", "rhythm": 0.25, "haspot": false, "gongchi": "工(□)", "word": ""}, "note110": {"note": "D4", "rhythm": 0.25, "haspot": false, "gongchi": "尺", "word": ""}, "note111": {"note": "D4", "rhythm": 0.25, "haspot": false, "gongchi": "尺(丶)", "word": "疑"}, "note112": {"note": "E4", "rhythm": 0.5, "haspot": false, "gongchi": "工(丶)", "word": ""}, "note113": {"note": "G4", "rhythm": 0.25, "haspot": false, "gongchi": "六", "word": ""}, "note114": {"note": "E4", "rhythm": 0.0625, "haspot": true, "gongchi": "工(丶)", "word": "憚"}, "note115": {"note": "G4", "rhythm": 0.03125, "haspot": false, "gongchi": "五", "word": ""}, "note116": {"note": "A5", "rhythm": 0.0625, "haspot": false, "gongchi": "六", "word": ""}, "note117": {"note": "G4", "rhythm": 0.0625, "haspot": false, "gongchi": "工", "word": ""}, "note118": {"note": "E4", "rhythm": 0.25, "haspot": false, "gongchi": "尺(━)", "word": ""}, "note119": {"note": "D4", "rhythm": 1.0, "haspot": false, "gongchi": "", "word": ""}, "juhao9": {"word": "。"}, "note120": {"note": "D4", "rhythm": 0.25, "haspot": false, "gongchi": "尺(□)", "word": "莫"}, "note121": {"note": "E4", "rhythm": 0.5, "haspot": true, "gongchi": "工(〇)", "word": ""}, "note122": {"note": "G4", "rhythm": 0.125, "haspot": false, "gongchi": "六", "word": ""}, "note123": {"note": "E4", "rhythm": 0.125, "haspot": false, "gongchi": "工(□)", "word": ""}, "note124": {"note": "E4", "rhythm": 0.125, "haspot": false, "gongchi": "尺", "word": ""}, "note125": {"note": "E4", "rhythm": 0.125, "haspot": false, "gongchi": "", "word": ""}, "note126": {"note": "D4", "rhythm": 0.125, "haspot": false, "gongchi": "", "word": ""}, "note127": {"note": "C4", "rhythm": 0.25, "haspot": false, "gongchi": "上(丶)", "word": "管"}, "note128": {"note": "D4", "rhythm": 0.25, "haspot": false, "gongchi": "尺", "word": ""}, "juhao10": {"word": "。"}, "note129": {"note": "A5", "rhythm": 0.5, "haspot": false, "gongchi": "五(□)", "word": "親"}, "note130": {"note": "C5", "rhythm": 0.25, "haspot": false, "gongchi": "仩", "word": ""}, "note131": {"note": "A5", "rhythm": 0.0625, "haspot": false, "gongchi": "五", "word": "去"}, "note132": {"note": "C5", "rhythm": 0.0625, "haspot": false, "gongchi": "六", "word": ""}, "note133": {"note": "G4", "rhythm": 0.125, "haspot": false, "gongchi": "", "word": ""}, "note134": {"note": "C4", "rhythm": 0.25, "haspot": false, "gongchi": "上(□)", "word": "贖"}, "note135": {"note": "D4", "rhythm": 0.25, "haspot": false, "gongchi": "尺", "word": ""}, "note136": {"note": "E4", "rhythm": 0.25, "haspot": true, "gongchi": "工(丶)", "word": "屍"}, "note137": {"note": "G4", "rhythm": 0.125, "haspot": false, "gongchi": "六", "word": ""}, "note138": {"note": "E4", "rhythm": 0.125, "haspot": false, "gongchi": "工(□)", "word": ""}, "note139": {"note": "E4", "rhythm": 0.125, "haspot": false, "gongchi": "尺", "word": ""}, "note140": {"note": "E4", "rhythm": 0.125, "haspot": false, "gongchi": "", "word": ""}, "note141": {"note": "D4", "rhythm": 0.125, "haspot": false, "gongchi": "", "word": ""}, "note142": {"note": "C4", "rhythm": 0.25, "haspot": false, "gongchi": "上(丶)", "word": "還"}, "note143": {"note": "D4", "rhythm": 0.25, "haspot": false, "gongchi": "尺", "word": ""}, "juhao11": {"word": "。"}, "note144": {"note": "A5", "rhythm": 0.25, "haspot": false, "gongchi": "五(□)", "word": "自"}, "note145": {"note": "G4", "rhythm": 0.125, "haspot": false, "gongchi": "六", "word": "有"}, "note146": {"note": "E4", "rhythm": 0.125, "haspot": false, "gongchi": "工", "word": ""}, "note147": {"note": "D4", "rhythm": 0.25, "haspot": false, "gongchi": "尺(丶)", "word": "巧"}, "note148": {"note": "C4", "rhythm": 0.25, "haspot": false, "gongchi": "上", "word": ""}, "note149": {"note": "D4", "rhythm": 0.25, "haspot": false, "gongchi": "尺(□)", "word": ""}, "note150": {"note": "E4", "rhythm": 0.125, "haspot": false, "gongchi": "工", "word": ""}, "note151": {"note": "D4", "rhythm": 0.125, "haspot": false, "gongchi": "", "word": ""}, "note152": {"note": "E4", "rhythm": 0.125, "haspot": false, "gongchi": "工(丶)", "word": "言"}, "note153": {"note": "G4", "rhythm": 0.25, "haspot": false, "gongchi": "六", "word": ""}, "note154": {"note": "A5", "rhythm": 0.125, "haspot": false, "gongchi": "五", "word": ""}, "note155": {"note": "G4", "rhythm": 1.0, "haspot": false, "gongchi": "六(□━)", "word": ""}, "note156": {"note": "G4", "rhythm": 0.5, "haspot": false, "gongchi": "六(□)", "word": "相"}, "note157": {"note": "A5", "rhythm": 0.25, "haspot": true, "gongchi": "五(丶)", "word": ""}, "note158": {"note": "G4", "rhythm": 0.125, "haspot": false, "gongchi": "六", "word": ""}, "note159": {"note": "E4", "rhythm": 0.25, "haspot": false, "gongchi": "工(□)", "word": ""}, "note160": {"note": "G4", "rhythm": 0.25, "haspot": false, "gongchi": "六", "word": ""}, "note161": {"note": "E4", "rhythm": 0.25, "haspot": false, "gongchi": "工(丶)", "word": "騙"}, "note162": {"note": "D4", "rhythm": 0.25, "haspot": false, "gongchi": "尺", "word": ""}, "juhao12": {"word": "。"}}