{"key": "D", "note1": {"note": "A5", "rhythm": 0.25, "haspot": false, "gongchi": "五", "word": "那"}, "note2": {"note": "G4", "rhythm": 0.25, "haspot": false, "gongchi": "工", "word": "日"}, "note3": {"note": "A5", "rhythm": 0.5, "haspot": false, "gongchi": "六", "word": ""}, "note4": {"note": "A5", "rhythm": 0.25, "haspot": false, "gongchi": "五(丶)", "word": "萱"}, "note5": {"note": "G4", "rhythm": 0.25, "haspot": false, "gongchi": "六", "word": "庭"}, "note6": {"note": "A5", "rhythm": 0.25, "haspot": true, "gongchi": "五(□)", "word": ""}, "note7": {"note": "G4", "rhythm": 0.125, "haspot": false, "gongchi": "六", "word": ""}, "note8": {"note": "E4", "rhythm": 0.25, "haspot": false, "gongchi": "工(丶)", "word": "萎"}, "note9": {"note": "G4", "rhythm": 0.25, "haspot": false, "gongchi": "六", "word": ""}, "note10": {"note": "E4", "rhythm": 0.25, "haspot": false, "gongchi": "工(□)", "word": "逝"}, "note11": {"note": "D4", "rhythm": 0.5, "haspot": false, "gongchi": "尺(━)", "word": ""}, "juhao1": {"word": "。"}, "note12": {"note": "A4", "rhythm": 0.25, "haspot": false, "gongchi": "四", "word": "我"}, "note13": {"note": "C4", "rhythm": 0.125, "haspot": false, "gongchi": "上(□)", "word": "孤"}, "note14": {"note": "D4", "rhythm": 0.125, "haspot": false, "gongchi": "尺", "word": ""}, "note15": {"note": "C4", "rhythm": 0.25, "haspot": false, "gongchi": "上", "word": "身"}, "note16": {"note": "A4", "rhythm": 0.25, "haspot": true, "gongchi": "四(丶)", "word": "寂"}, "note17": {"note": "G3", "rhythm": 0.125, "haspot": false, "gongchi": "合", "word": ""}, "note18": {"note": "A4", "rhythm": 0.125, "haspot": false, "gongchi": "四(□)", "word": "守"}, "note19": {"note": "C4", "rhythm": 0.125, "haspot": false, "gongchi": "上", "word": ""}, "note20": {"note": "D4", "rhythm": 0.5, "haspot": false, "gongchi": "尺(━)", "word": ""}, "note21": {"note": "D4", "rhythm": 0.125, "haspot": false, "gongchi": "尺", "word": "蓬"}, "note22": {"note": "E4", "rhythm": 0.25, "haspot": false, "gongchi": "工(∟)", "word": ""}, "note23": {"note": "G4", "rhythm": 0.125, "haspot": false, "gongchi": "六", "word": ""}, "note24": {"note": "E4", "rhythm": 0.25, "haspot": false, "gongchi": "工", "word": ""}, "note25": {"note": "", "rhythm": "", "haspot": false, "gongchi": "尺", "word": ""}, "note26": {"note": "D4", "rhythm": 0.5, "haspot": false, "gongchi": "尺(丶)", "word": "居"}, "juhao2": {"word": "。"}, "note27": {"note": "C4", "rhythm": 0.25, "haspot": false, "gongchi": "上(□)", "word": "辛"}, "note28": {"note": "A4", "rhythm": 0.25, "haspot": false, "gongchi": "四", "word": "勤"}, "note29": {"note": "A4", "rhythm": 0.25, "haspot": false, "gongchi": "四(丶)", "word": "歷"}, "note30": {"note": "C4", "rhythm": 0.125, "haspot": false, "gongchi": "上", "word": ""}, "note31": {"note": "D4", "rhythm": 0.125, "haspot": false, "gongchi": "尺", "word": ""}, "note32": {"note": "E4", "rhythm": 0.25, "haspot": false, "gongchi": "工(丶)", "word": "盡"}, "note33": {"note": "D4", "rhythm": 0.5, "haspot": false, "gongchi": "尺(━)", "word": ""}, "juhao3": {"word": "。"}, "note34": {"note": "G4", "rhythm": 0.25, "haspot": false, "gongchi": "六", "word": "今"}, "note35": {"note": "A5", "rhythm": 0.125, "haspot": true, "gongchi": "五(□)", "word": ""}, "note36": {"note": "G4", "rhythm": 0.0625, "haspot": false, "gongchi": "六", "word": ""}, "note37": {"note": "E4", "rhythm": 0.125, "haspot": false, "gongchi": "工", "word": "日"}, "note38": {"note": "G4", "rhythm": 0.125, "haspot": false, "gongchi": "六", "word": ""}, "note39": {"note": "D5", "rhythm": 0.0625, "haspot": false, "gongchi": "尺(丶)", "word": "佩"}, "note40": {"note": "E5", "rhythm": 0.0625, "haspot": false, "gongchi": "仩", "word": ""}, "note41": {"note": "C5", "rhythm": 0.125, "haspot": false, "gongchi": "", "word": ""}, "note42": {"note": "A5", "rhythm": 0.25, "haspot": true, "gongchi": "五(丶)", "word": "簪"}, "note43": {"note": "C5", "rhythm": 0.125, "haspot": false, "gongchi": "仩", "word": ""}, "note44": {"note": "A5", "rhythm": 0.25, "haspot": false, "gongchi": "五", "word": ""}, "note45": {"note": "G4", "rhythm": 0.5, "haspot": false, "gongchi": "六(丶)", "word": "裾"}, "juhao4": {"word": "。"}, "note46": {"note": "G4", "rhythm": 0.125, "haspot": false, "gongchi": "六(丶)", "word": "扊"}, "note47": {"note": "E4", "rhythm": 0.0625, "haspot": false, "gongchi": "工", "word": ""}, "note48": {"note": "D4", "rhythm": 0.0625, "haspot": false, "gongchi": "", "word": ""}, "note49": {"note": "E4", "rhythm": 0.25, "haspot": false, "gongchi": "工", "word": "扅"}, "note50": {"note": "E4", "rhythm": 0.125, "haspot": false, "gongchi": "工(丶)", "word": "重"}, "note51": {"note": "G4", "rhythm": 0.125, "haspot": false, "gongchi": "六", "word": ""}, "note52": {"note": "A5", "rhythm": 0.25, "haspot": false, "gongchi": "五", "word": "效"}, "note53": {"note": "G4", "rhythm": 0.25, "haspot": true, "gongchi": "六", "word": ""}, "note54": {"note": "E4", "rhythm": 0.125, "haspot": false, "gongchi": "工", "word": ""}, "note55": {"note": "D4", "rhythm": 0.25, "haspot": false, "gongchi": "尺(丶)", "word": "鴛"}, "note56": {"note": "E4", "rhythm": 0.125, "haspot": true, "gongchi": "工", "word": ""}, "note57": {"note": "D4", "rhythm": 0.0625, "haspot": false, "gongchi": "尺", "word": ""}, "note58": {"note": "C4", "rhythm": 0.5, "haspot": false, "gongchi": "上(□)", "word": "鴦"}, "note59": {"note": "D4", "rhythm": 0.25, "haspot": false, "gongchi": "尺(丶)", "word": "戲"}, "note60": {"note": "C4", "rhythm": 0.25, "haspot": false, "gongchi": "工", "word": ""}, "note61": {"note": "A4", "rhythm": 0.5, "haspot": false, "gongchi": "四(□)", "word": ""}, "juhao5": {"word": "。"}, "note62": {"note": "C4", "rhythm": 0.25, "haspot": false, "gongchi": "上(丶)", "word": "歡"}, "note63": {"note": "A4", "rhythm": 0.25, "haspot": false, "gongchi": "四", "word": "諧"}, "note64": {"note": "C4", "rhythm": 0.25, "haspot": false, "gongchi": "上(□)", "word": ""}, "note65": {"note": "A5", "rhythm": 0.25, "haspot": false, "gongchi": "六", "word": "伉"}, "note66": {"note": "D4", "rhythm": 0.25, "haspot": false, "gongchi": "尺(丶)", "word": "儷"}, "note67": {"note": "C4", "rhythm": 0.25, "haspot": false, "gongchi": "上", "word": ""}, "note68": {"note": "A4", "rhythm": 0.5, "haspot": false, "gongchi": "四(□)", "word": ""}, "juhao6": {"word": "。"}, "note69": {"note": "G4", "rhythm": 0.25, "haspot": false, "gongchi": "六(丶)", "word": "唱"}, "note70": {"note": "C4", "rhythm": 0.125, "haspot": false, "gongchi": "上", "word": "隨"}, "note71": {"note": "D4", "rhythm": 0.125, "haspot": false, "gongchi": "尺(□)", "word": ""}, "note72": {"note": "D4", "rhythm": 0.0625, "haspot": false, "gongchi": "上", "word": ""}, "note73": {"note": "C4", "rhythm": 0.0625, "haspot": false, "gongchi": "", "word": ""}, "note74": {"note": "A4", "rhythm": 0.125, "haspot": false, "gongchi": "", "word": ""}, "note75": {"note": "G3", "rhythm": 0.25, "haspot": false, "gongchi": "合", "word": "永"}, "note76": {"note": "A4", "rhythm": 0.125, "haspot": false, "gongchi": "四(丶)", "word": "娛"}, "note77": {"note": "C4", "rhythm": 0.25, "haspot": false, "gongchi": "上", "word": ""}, "note78": {"note": "D4", "rhythm": 0.125, "haspot": false, "gongchi": "尺", "word": ""}, "note79": {"note": "C4", "rhythm": 0.5, "haspot": false, "gongchi": "上(□)", "word": ""}, "juhao7": {"word": "。"}, "note80": {"note": "E4", "rhythm": 0.25, "haspot": false, "gongchi": "工(丶)", "word": "齊"}, "note81": {"note": "E4", "rhythm": 0.25, "haspot": false, "gongchi": "工", "word": "眉"}, "note82": {"note": "G4", "rhythm": 0.25, "haspot": false, "gongchi": "六(□)", "word": ""}, "note83": {"note": "E4", "rhythm": 0.125, "haspot": false, "gongchi": "工", "word": "舉"}, "note84": {"note": "G4", "rhythm": 0.125, "haspot": false, "gongchi": "六", "word": ""}, "note85": {"note": "A5", "rhythm": 0.25, "haspot": false, "gongchi": "五(丶)", "word": "案"}, "note86": {"note": "G4", "rhythm": 0.25, "haspot": false, "gongchi": "六", "word": ""}, "note87": {"note": "E4", "rhythm": 0.5, "haspot": false, "gongchi": "工(□)", "word": ""}, "juhao8": {"word": "。"}, "note88": {"note": "C4", "rhythm": 0.25, "haspot": false, "gongchi": "上", "word": "偕"}, "note89": {"note": "A4", "rhythm": 0.25, "haspot": false, "gongchi": "四", "word": "老"}, "note90": {"note": "C4", "rhythm": 0.125, "haspot": true, "gongchi": "上(□)", "word": ""}, "note91": {"note": "A4", "rhythm": 0.0625, "haspot": false, "gongchi": "", "word": ""}, "note92": {"note": "G3", "rhythm": 0.25, "haspot": false, "gongchi": "合", "word": "永"}, "note93": {"note": "A4", "rhythm": 0.25, "haspot": false, "gongchi": "四(丶)", "word": "隨"}, "note94": {"note": "C4", "rhythm": 0.5, "haspot": false, "gongchi": "上(丶)", "word": ""}, "juhao9": {"word": "。"}, "note95": {"note": "A4", "rhythm": 0.25, "haspot": false, "gongchi": "工(丶)", "word": "皇"}, "note96": {"note": "D4", "rhythm": 0.25, "haspot": false, "gongchi": "五(∟)", "word": ""}, "note97": {"note": "E4", "rhythm": 0.25, "haspot": false, "gongchi": "仩", "word": ""}, "note98": {"note": "", "rhythm": "", "haspot": false, "gongchi": "五", "word": ""}, "note99": {"note": "C4", "rhythm": 0.5, "haspot": false, "gongchi": "六(丶)", "word": "恩"}, "note100": {"note": "", "rhythm": "", "haspot": false, "gongchi": "五", "word": ""}, "note101": {"note": "", "rhythm": "", "haspot": false, "gongchi": "六", "word": ""}, "note102": {"note": "", "rhythm": "", "haspot": false, "gongchi": "工", "word": ""}, "note103": {"note": "", "rhythm": "", "haspot": false, "gongchi": "六", "word": ""}, "note104": {"note": "D4", "rhythm": 0.25, "haspot": false, "gongchi": "五(丶)", "word": "莘"}, "note105": {"note": "C4", "rhythm": 0.25, "haspot": false, "gongchi": "五", "word": ""}, "note106": {"note": "A4", "rhythm": 0.25, "haspot": false, "gongchi": "六", "word": ""}, "note107": {"note": "", "rhythm": "", "haspot": false, "gongchi": "工", "word": ""}, "note108": {"note": "", "rhythm": "", "haspot": false, "gongchi": "尺(□)", "word": ""}, "note109": {"note": "", "rhythm": "", "haspot": false, "gongchi": "工(□)", "word": ""}, "note110": {"note": "", "rhythm": "", "haspot": false, "gongchi": "尺", "word": ""}, "juhao10": {"word": "。"}, "note111": {"note": "G4", "rhythm": 0.25, "haspot": true, "gongchi": "上(〇∟)", "word": "福"}, "note112": {"note": "A5", "rhythm": 0.125, "haspot": false, "gongchi": "尺", "word": ""}, "note113": {"note": "G4", "rhythm": 0.25, "haspot": false, "gongchi": "", "word": ""}, "note114": {"note": "A5", "rhythm": 0.25, "haspot": false, "gongchi": "工(〇)", "word": "慶"}, "note115": {"note": "A5", "rhythm": 0.0625, "haspot": false, "gongchi": "尺", "word": ""}, "note116": {"note": "G4", "rhythm": 0.0625, "haspot": false, "gongchi": "上(□)", "word": ""}, "note117": {"note": "E4", "rhythm": 0.125, "haspot": false, "gongchi": "四", "word": ""}, "note118": {"note": "D4", "rhythm": 0.25, "haspot": false, "gongchi": "合(丶)", "word": "齊"}, "note119": {"note": "E4", "rhythm": 0.25, "haspot": false, "gongchi": "四", "word": ""}, "juhao11": {"word": "。"}, "note120": {"note": "G4", "rhythm": 0.125, "haspot": false, "gongchi": "六(□)", "word": "蒼"}, "note121": {"note": "A5", "rhythm": 0.125, "haspot": false, "gongchi": "五(〇)", "word": ""}, "note122": {"note": "G4", "rhythm": 0.25, "haspot": false, "gongchi": "六(□)", "word": "天"}, "note123": {"note": "G4", "rhythm": 0.25, "haspot": false, "gongchi": "六(丶□)", "word": "端"}, "note124": {"note": "A5", "rhythm": 0.125, "haspot": true, "gongchi": "五", "word": ""}, "note125": {"note": "G4", "rhythm": 0.0625, "haspot": false, "gongchi": "", "word": ""}, "note126": {"note": "E4", "rhythm": 0.5, "haspot": false, "gongchi": "六(〇)", "word": "不"}, "note127": {"note": "", "rhythm": "", "haspot": false, "gongchi": "五", "word": ""}, "note128": {"note": "", "rhythm": "", "haspot": false, "gongchi": "六", "word": ""}, "note129": {"note": "", "rhythm": "", "haspot": false, "gongchi": "工(□)", "word": ""}, "note130": {"note": "", "rhythm": "", "haspot": false, "gongchi": "尺", "word": ""}, "note131": {"note": "E4", "rhythm": 0.5, "haspot": false, "gongchi": "六(〇)", "word": "不"}, "note132": {"note": "", "rhythm": "", "haspot": false, "gongchi": "五", "word": ""}, "note133": {"note": "", "rhythm": "", "haspot": false, "gongchi": "六", "word": ""}, "note134": {"note": "", "rhythm": "", "haspot": false, "gongchi": "工(□)", "word": ""}, "note135": {"note": "", "rhythm": "", "haspot": false, "gongchi": "尺", "word": ""}, "note136": {"note": "A4", "rhythm": 0.125, "haspot": false, "gongchi": "四(□)", "word": "男"}, "note137": {"note": "C4", "rhythm": 0.25, "haspot": false, "gongchi": "上", "word": ""}, "note138": {"note": "D4", "rhythm": 0.125, "haspot": false, "gongchi": "尺", "word": ""}, "note139": {"note": "D4", "rhythm": 0.0625, "haspot": false, "gongchi": "上(□)", "word": ""}, "note140": {"note": "C4", "rhythm": 0.0625, "haspot": false, "gongchi": "四", "word": ""}, "note141": {"note": "A4", "rhythm": 0.125, "haspot": false, "gongchi": "", "word": ""}, "note142": {"note": "G3", "rhythm": 0.25, "haspot": false, "gongchi": "合(丶)", "word": "兒"}, "note143": {"note": "A4", "rhythm": 0.25, "haspot": false, "gongchi": "四", "word": ""}, "juhao12": {"word": "。"}}